MANIFEST.in
setup.py
deeperlib/__init__.py
deeperlib.egg-info/PKG-INFO
deeperlib.egg-info/SOURCES.txt
deeperlib.egg-info/dependency_links.txt
deeperlib.egg-info/requires.txt
deeperlib.egg-info/top_level.txt
deeperlib/api/__init__.py
deeperlib/api/simapi.py
deeperlib/api/simthread.py
deeperlib/api/aminer/__init__.py
deeperlib/api/aminer/advanced_personapi.py
deeperlib/api/aminer/advanced_publapi.py
deeperlib/api/aminer/personapi.py
deeperlib/api/aminer/publapi.py
deeperlib/api/dblp/__init__.py
deeperlib/api/dblp/authorapi.py
deeperlib/api/dblp/publapi.py
deeperlib/api/dblp/venueapi.py
deeperlib/api/yelp/__init__.py
deeperlib/api/yelp/searchapi.py
deeperlib/core/__init__.py
deeperlib/core/smartcrawl.py
deeperlib/core/utils.py
deeperlib/data_processing/__init__.py
deeperlib/data_processing/data_process.py
deeperlib/data_processing/hidden_data.py
deeperlib/data_processing/json2csv.py
deeperlib/data_processing/local_data.py
deeperlib/data_processing/sample_data.py
deeperlib/entity_resolution/__init__.py
deeperlib/entity_resolution/simjoin.py
deeperlib/estimator/__init__.py
deeperlib/estimator/aggregation.py
deeperlib/estimator/sampler.py
deeperlib/extensions/__init__.py
deeperlib/extensions/Darwin_64/__init__.py
deeperlib/extensions/Darwin_64/fim.so
deeperlib/extensions/Linux_32/__init__.py
deeperlib/extensions/Linux_32/fim.so
deeperlib/extensions/Linux_64/__init__.py
deeperlib/extensions/Linux_64/fim.so
deeperlib/extensions/Windows_32/__init__.py
deeperlib/extensions/Windows_32/fim.pyd
deeperlib/extensions/Windows_64/__init__.py
deeperlib/extensions/Windows_64/fim.pyd