Metadata-Version: 1.1
Name: deeperlib
Version: 0.2a0
Summary: data integration, data enrichment, entity resolution
Home-page: https://github.com/sfu-db/deeper
Author: yongjunhe
Author-email: 141250047@smail.nju.edu.cn
License: UNKNOWN
Platform: Linux/Unix
Platform: Microsoft Windows
Platform: MacOS
Classifier: Intended Audience :: Developers
Classifier: Programming Language :: Python
Classifier: Programming Language :: Python :: Implementation
Classifier: Programming Language :: Python :: 2
Classifier: Programming Language :: Python :: 2.7
Classifier: Topic :: Software Development :: Libraries
